uv_dep_tree/__init__.py
uv_dep_tree/__main__.py
uv_dep_tree-0.1.0.dist-info/METADATA
uv_dep_tree-0.1.0.dist-info/WHEEL
uv_dep_tree-0.1.0.dist-info/entry_points.txt
uv_dep_tree-0.1.0.dist-info/licenses/LICENSE
uv_dep_tree-0.1.0.dist-info/RECORD
