Metadata-Version: 2.4
Name: uv-dep-tree
Version: 0.1.0
Summary: Visualize uv.lock dependency sizes as a nested tree with deduplication metrics
Project-URL: Homepage, https://github.com/p120ph37/uv-dep-tree
Project-URL: Repository, https://github.com/p120ph37/uv-dep-tree
Project-URL: Issues, https://github.com/p120ph37/uv-dep-tree/issues
Author: Aaron Meriwether
License-Expression: MIT
License-File: LICENSE
Keywords: dependencies,lock,tree,uv,visualization
Classifier: Development Status :: 4 - Beta
Classifier: Environment :: Console
Classifier: Intended Audience :: Developers
Classifier: License :: OSI Approved :: MIT License
Classifier: Programming Language :: Python :: 3
Classifier: Programming Language :: Python :: 3.11
Classifier: Programming Language :: Python :: 3.12
Classifier: Programming Language :: Python :: 3.13
Classifier: Topic :: Software Development :: Build Tools
Requires-Python: >=3.11
